Workbook

Sheet Assumptions
A1: Balance | B1: 5000000000
A2: Equity | B2: 3700000000
A3: Debt | B3: =-B1*B4*(1+B8)^B5 -> -5.5452683e+09
A4: Asset Multiplier | B4: 1
A5: Debt Interest Period(Year) | B5: 0.5
A6: Debt Payment Period(Year) | B6: 0.5
A7: Exemption Period(Month) | B7: 11
A8: Interest rate / Y | B8: 0.23
A9: Return rate / Y | B9: 0.38
A10: Interest rate / D | B10: =(1+B9)^(1/365) -> 1.0008828
A11: Depreciation rate / M | B11: 0.025

Sheet CashFlow
A1: Date | B1: Month | C1: Assets | D1: Income | E1: Debt | F1: Remained Debt | H1: Return | I1: Asset After Debt | K1: CashFlow | L1: Discounted Value | O1: NPV
A2: 46143 | B2: 1 | C2: =Assumptions!$B$2+D2-SUM($E$2:E2) -> 3.8363964e+09 | D2: =Assumptions!$B$1*(Assumptions!$B$10^30.5)-Assumptions!B1 -> 1.3639637e+08 | E2: 0 | F2: =0 -> 0 | H2: 0 | I2: 0 | K2: =IF(B2>Assumptions!$B$6*12+Assumptions!$B$7,"",C2) -> 3.8363964e+09 | L2: =IF(B2>Assumptions!$B$6*12+Assumptions!$B$7,"",K2/(1+Assumptions!$B$11)^B2) -> 3.7428257e+09 | O2: =NPV(Assumptions!$B$11,K2:K72,A2:A72)/COUNT(L2:L72) -> 2.9919183e+09
A3: 46199 | B3: =B2+1 -> 2 | C3: =C2+D3+E3 -> 3.9410505e+09 | D3: =C2*Assumptions!$B$10^30.5-C2 -> 1.0465411e+08 | E3: =IF(CashFlow!B3<Assumptions!$B$7+1,0,IF(AND(B3>=Assumptions!$B$7,SUM($E$2:E2)<>Assumptions!$B$3),Assumptions!$B$3/(Assumptions!$B$6*12),IF(Assumptions!$B$3=SUM($E$3:E3)=0,0,0))) -> 0 | F3: =IF(B3<Assumptions!$B$7+1,0,IF(E2<0,Assumptions!$B$3-SUM($E$3:E3),0)) -> 0 | H3: 0 | I3: 0 | K3: =IF(B3>Assumptions!$B$6*12+Assumptions!$B$7,"",C3) -> 3.9410505e+09 | L3: =IF(B3>Assumptions!$B$6*12+Assumptions!$B$7,"",K3/(1+Assumptions!$B$11)^B3) -> 3.7511486e+09 | O3: =SUM(L2:L72)/COUNT(L2:L72) -> 2.9918583e+09
A4: 46229 | B4: =B3+1 -> 3 | C4: =C3+D4+E4 -> 4.0485595e+09 | D4: =C3*Assumptions!$B$10^30.5-C3 -> 1.07509e+08 | E4: =IF(CashFlow!B4<Assumptions!$B$7+1,0,IF(AND(B4>=Assumptions!$B$7,SUM($E$2:E3)<>Assumptions!$B$3),Assumptions!$B$3/(Assumptions!$B$6*12),IF(Assumptions!$B$3=SUM($E$3:E4)=0,0,0))) -> 0 | F4: =IF(B4<Assumptions!$B$7+1,0,IF(E3<0,Assumptions!$B$3-SUM($E$3:E4),0)) -> 0 | H4: 0 | I4: 0 | K4: =IF(B4>Assumptions!$B$6*12+Assumptions!$B$7,"",C4) -> 4.0485595e+09 | L4: =IF(B4>Assumptions!$B$6*12+Assumptions!$B$7,"",K4/(1+Assumptions!$B$11)^B4) -> 3.75949e+09
A5: 46260 | B5: =B4+1 -> 4 | C5: =C4+D5+E5 -> 4.1590013e+09 | D5: =C4*Assumptions!$B$10^30.5-C4 -> 1.1044177e+08 | E5: =IF(CashFlow!B5<Assumptions!$B$7+1,0,IF(AND(B5>=Assumptions!$B$7,SUM($E$2:E4)<>Assumptions!$B$3),Assumptions!$B$3/(Assumptions!$B$6*12),IF(Assumptions!$B$3=SUM($E$3:E5)=0,0,0))) -> 0 | F5: =IF(B5<Assumptions!$B$7+1,0,IF(E4<0,Assumptions!$B$3-SUM($E$3:E5),0)) -> 0 | H5: 0 | I5: 0 | K5: =IF(B5>Assumptions!$B$6*12+Assumptions!$B$7,"",C5) -> 4.1590013e+09 | L5: =IF(B5>Assumptions!$B$6*12+Assumptions!$B$7,"",K5/(1+Assumptions!$B$11)^B5) -> 3.7678499e+09 | O5: Total Debt
A6: 46291 | B6: =B5+1 -> 5 | C6: =C5+D6+E6 -> 4.2724558e+09 | D6: =C5*Assumptions!$B$10^30.5-C5 -> 1.1345454e+08 | E6: =IF(CashFlow!B6<Assumptions!$B$7+1,0,IF(AND(B6>=Assumptions!$B$7,SUM($E$2:E5)<>Assumptions!$B$3),Assumptions!$B$3/(Assumptions!$B$6*12),IF(Assumptions!$B$3=SUM($E$3:E6)=0,0,0))) -> 0 | F6: =IF(B6<Assumptions!$B$7+1,0,IF(E5<0,Assumptions!$B$3-SUM($E$3:E6),0)) -> 0 | H6: 0 | I6: 0 | K6: =IF(B6>Assumptions!$B$6*12+Assumptions!$B$7,"",C6) -> 4.2724558e+09 | L6: =IF(B6>Assumptions!$B$6*12+Assumptions!$B$7,"",K6/(1+Assumptions!$B$11)^B6) -> 3.7762284e+09 | O6: =Assumptions!B3 -> -5.5452683e+09
A7: 46321 | B7: =B6+1 -> 6 | C7: =C6+D7+E7 -> 4.3890053e+09 | D7: =C6*Assumptions!$B$10^30.5-C6 -> 1.165495e+08 | E7: =IF(CashFlow!B7<Assumptions!$B$7+1,0,IF(AND(B7>=Assumptions!$B$7,SUM($E$2:E6)<>Assumptions!$B$3),Assumptions!$B$3/(Assumptions!$B$6*12),IF(Assumptions!$B$3=SUM($E$3:E7)=0,0,0))) -> 0 | F7: =IF(B7<Assumptions!$B$7+1,0,IF(E6<0,Assumptions!$B$3-SUM($E$3:E7),0)) -> 0 | H7: 0 | I7: 0 | K7: =IF(B7>Assumptions!$B$6*12+Assumptions!$B$7,"",C7) -> 4.3890053e+09 | L7: =IF(B7>Assumptions!$B$6*12+Assumptions!$B$7,"",K7/(1+Assumptions!$B$11)^B7) -> 3.7846255e+09
A8: 46352 | B8: =B7+1 -> 7 | C8: =C7+D8+E8 -> 4.5087342e+09 | D8: =C7*Assumptions!$B$10^30.5-C7 -> 1.1972888e+08 | E8: =IF(CashFlow!B8<Assumptions!$B$7+1,0,IF(AND(B8>=Assumptions!$B$7,SUM($E$2:E7)<>Assumptions!$B$3),Assumptions!$B$3/(Assumptions!$B$6*12),IF(Assumptions!$B$3=SUM($E$3:E8)=0,0,0))) -> 0 | F8: =IF(B8<Assumptions!$B$7+1,0,IF(E7<0,Assumptions!$B$3-SUM($E$3:E8),0)) -> 0 | H8: 0 | I8: 0 | K8: =IF(B8>Assumptions!$B$6*12+Assumptions!$B$7,"",C8) -> 4.5087342e+09 | L8: =IF(B8>Assumptions!$B$6*12+Assumptions!$B$7,"",K8/(1+Assumptions!$B$11)^B8) -> 3.7930413e+09
A9: 46382 | B9: =B8+1 -> 8 | C9: =C8+D9+E9 -> 4.6317292e+09 | D9: =C8*Assumptions!$B$10^30.5-C8 -> 1.22995e+08 | E9: =IF(CashFlow!B9<Assumptions!$B$7+1,0,IF(AND(B9>=Assumptions!$B$7,SUM($E$2:E8)<>Assumptions!$B$3),Assumptions!$B$3/(Assumptions!$B$6*12),IF(Assumptions!$B$3=SUM($E$3:E9)=0,0,0))) -> 0 | F9: =IF(B9<Assumptions!$B$7+1,0,IF(E8<0,Assumptions!$B$3-SUM($E$3:E9),0)) -> 0 | H9: 0 | I9: 0 | K9: =IF(B9>Assumptions!$B$6*12+Assumptions!$B$7,"",C9) -> 4.6317292e+09 | L9: =IF(B9>Assumptions!$B$6*12+Assumptions!$B$7,"",K9/(1+Assumptions!$B$11)^B9) -> 3.8014758e+09
A10: 46413 | B10: =B9+1 -> 9 | C10: =C9+D10+E10 -> 4.7580794e+09 | D10: =C9*Assumptions!$B$10^30.5-C9 -> 1.2635021e+08 | E10: =IF(CashFlow!B10<Assumptions!$B$7+1,0,IF(AND(B10>=Assumptions!$B$7,SUM($E$2:E9)<>Assumptions!$B$3),Assumptions!$B$3/(Assumptions!$B$6*12),IF(Assumptions!$B$3=SUM($E$3:E10)=0,0,0))) -> 0 | F10: =IF(B10<Assumptions!$B$7+1,0,IF(E9<0,Assumptions!$B$3-SUM($E$3:E10),0)) -> 0 | H10: 0 | I10: 0 | K10: =IF(B10>Assumptions!$B$6*12+Assumptions!$B$7,"",C10) -> 4.7580794e+09 | L10: =IF(B10>Assumptions!$B$6*12+Assumptions!$B$7,"",K10/(1+Assumptions!$B$11)^B10) -> 3.8099291e+09
A11: 46444 | B11: =B10+1 -> 10 | C11: =C10+D11+E11 -> 4.8878763e+09 | D11: =C10*Assumptions!$B$10^30.5-C10 -> 1.2979696e+08 | E11: =IF(CashFlow!B11<Assumptions!$B$7+1,0,IF(AND(B11>=Assumptions!$B$7,SUM($E$2:E10)<>Assumptions!$B$3),Assumptions!$B$3/(Assumptions!$B$6*12),IF(Assumptions!$B$3=SUM($E$3:E11)=0,0,0))) -> 0 | F11: =IF(B11<Assumptions!$B$7+1,0,IF(E10<0,Assumptions!$B$3-SUM($E$3:E11),0)) -> 0 | H11: 0 | I11: 0 | K11: =IF(B11>Assumptions!$B$6*12+Assumptions!$B$7,"",C11) -> 4.8878763e+09 | L11: =IF(B11>Assumptions!$B$6*12+Assumptions!$B$7,"",K11/(1+Assumptions!$B$11)^B11) -> 3.8184012e+09
A12: 46472 | B12: =B11+1 -> 11 | C12: =C11+D12+E12 -> 5.0212141e+09 | D12: =C11*Assumptions!$B$10^30.5-C11 -> 1.3333772e+08 | E12: =IF(CashFlow!B12<Assumptions!$B$7+1,0,IF(AND(B12>=Assumptions!$B$7,SUM($E$2:E11)<>Assumptions!$B$3),Assumptions!$B$3/(Assumptions!$B$6*12),IF(Assumptions!$B$3=SUM($E$3:E12)=0,0,0))) -> 0 | F12: =IF(B12<Assumptions!$B$7+1,0,IF(E11<0,Assumptions!$B$3-SUM($E$3:E12),0)) -> 0 | H12: 0 | I12: 0 | K12: =IF(B12>Assumptions!$B$6*12+Assumptions!$B$7,"",C12) -> 5.0212141e+09 | L12: =IF(B12>Assumptions!$B$6*12+Assumptions!$B$7,"",K12/(1+Assumptions!$B$11)^B12) -> 3.8268921e+09
A13: 46503 | B13: =B12+1 -> 12 | C13: =C12+D13+E13 -> 4.2339778e+09 | D13: =C12*Assumptions!$B$10^30.5-C12 -> 1.3697508e+08 | E13: =IF(CashFlow!B13<Assumptions!$B$7+1,0,IF(AND(B13>=Assumptions!$B$7,SUM($E$2:E12)<>Assumptions!$B$3),Assumptions!$B$3/(Assumptions!$B$6*12),IF(Assumptions!$B$3=SUM($E$3:E13)=0,0,0))) -> -9.2421138e+08 | F13: =IF(B13<Assumptions!$B$7+1,0,IF(E12<0,Assumptions!$B$3-SUM($E$3:E13),0)) -> 0 | H13: 0 | I13: 0 | K13: =IF(B13>Assumptions!$B$6*12+Assumptions!$B$7,"",C13) -> 4.2339778e+09 | L13: =IF(B13>Assumptions!$B$6*12+Assumptions!$B$7,"",K13/(1+Assumptions!$B$11)^B13) -> 3.1481991e+09
A14: 46533 | B14: =B13+1 -> 13 | C14: =C13+D14+E14 -> 3.4252662e+09 | D14: =C13*Assumptions!$B$10^30.5-C13 -> 1.1549984e+08 | E14: =IF(CashFlow!B14<Assumptions!$B$7+1,0,IF(AND(B14>=Assumptions!$B$7,SUM($E$2:E13)<>Assumptions!$B$3),Assumptions!$B$3/(Assumptions!$B$6*12),IF(Assumptions!$B$3=SUM($E$3:E14)=0,0,0))) -> -9.2421138e+08 | F14: =IF(B14<Assumptions!$B$7+1,0,IF(E13<0,Assumptions!$B$3-SUM($E$3:E14),0)) -> -3.6968455e+09 | H14: =IF(E14=0,D14,0) -> 0 | I14: =IF(E14=0,C14+D14,0) -> 0 | K14: =IF(B14>Assumptions!$B$6*12+Assumptions!$B$7,"",C14) -> 3.4252662e+09 | L14: =IF(B14>Assumptions!$B$6*12+Assumptions!$B$7,"",K14/(1+Assumptions!$B$11)^B14) -> 2.4847579e+09
A15: 46564 | B15: =B14+1 -> 14 | C15: =C14+D15+E15 -> 2.5944936e+09 | D15: =C14*Assumptions!$B$10^30.5-C14 -> 93438779 | E15: =IF(CashFlow!B15<Assumptions!$B$7+1,0,IF(AND(B15>=Assumptions!$B$7,SUM($E$2:E14)<>Assumptions!$B$3),Assumptions!$B$3/(Assumptions!$B$6*12),IF(Assumptions!$B$3=SUM($E$3:E15)=0,0,0))) -> -9.2421138e+08 | F15: =IF(B15<Assumptions!$B$7+1,0,IF(E14<0,Assumptions!$B$3-SUM($E$3:E15),0)) -> -2.7726341e+09 | H15: =IF(E15=0,D15,0) -> 0 | I15: =IF(E15=0,C15+D15,0) -> 0 | K15: =IF(B15>Assumptions!$B$6*12+Assumptions!$B$7,"",C15) -> 2.5944936e+09 | L15: =IF(B15>Assumptions!$B$6*12+Assumptions!$B$7,"",K15/(1+Assumptions!$B$11)^B15) -> 1.8361937e+09
A16: 46594 | B16: =B15+1 -> 15 | C16: =C15+D16+E16 -> 1.7410582e+09 | D16: =C15*Assumptions!$B$10^30.5-C15 -> 70775905 | E16: =IF(CashFlow!B16<Assumptions!$B$7+1,0,IF(AND(B16>=Assumptions!$B$7,SUM($E$2:E15)<>Assumptions!$B$3),Assumptions!$B$3/(Assumptions!$B$6*12),IF(Assumptions!$B$3=SUM($E$3:E16)=0,0,0))) -> -9.2421138e+08 | F16: =IF(B16<Assumptions!$B$7+1,0,IF(E15<0,Assumptions!$B$3-SUM($E$3:E16),0)) -> -1.8484228e+09 | H16: =IF(E16=0,D16,0) -> 0 | I16: =IF(E16=0,C16+D16,0) -> 0 | K16: =IF(B16>Assumptions!$B$6*12+Assumptions!$B$7,"",C16) -> 1.7410582e+09 | L16: =IF(B16>Assumptions!$B$6*12+Assumptions!$B$7,"",K16/(1+Assumptions!$B$11)^B16) -> 1.2021407e+09
A17: 46625 | B17: =B16+1 -> 16 | C17: =C16+D17+E17 -> 8.6434159e+08 | D17: =C16*Assumptions!$B$10^30.5-C16 -> 47494804 | E17: =IF(CashFlow!B17<Assumptions!$B$7+1,0,IF(AND(B17>=Assumptions!$B$7,SUM($E$2:E16)<>Assumptions!$B$3),Assumptions!$B$3/(Assumptions!$B$6*12),IF(Assumptions!$B$3=SUM($E$3:E17)=0,0,0))) -> -9.2421138e+08 | F17: =IF(B17<Assumptions!$B$7+1,0,IF(E16<0,Assumptions!$B$3-SUM($E$3:E17),0)) -> -9.2421138e+08 | H17: =IF(E17=0,D17,0) -> 0 | I17: =IF(E17=0,C17+D17,0) -> 0 | K17: =IF(B17>Assumptions!$B$6*12+Assumptions!$B$7,"",C17) -> 8.6434159e+08 | L17: =IF(B17>Assumptions!$B$6*12+Assumptions!$B$7,"",K17/(1+Assumptions!$B$11)^B17) -> 5.8224204e+08
A18: 46656 | B18: =B17+1 -> 17 | C18: =C17+D18+E18 -> -36291177 | D18: =C17*Assumptions!$B$10^30.5-C17 -> 23578612 | E18: =IF(CashFlow!B18<Assumptions!$B$7+1,0,IF(AND(B18>=Assumptions!$B$7,SUM($E$2:E17)<>Assumptions!$B$3),Assumptions!$B$3/(Assumptions!$B$6*12),IF(Assumptions!$B$3=SUM($E$3:E18)=0,0,0))) -> -9.2421138e+08 | F18: =IF(B18<Assumptions!$B$7+1,0,IF(E17<0,Assumptions!$B$3-SUM($E$3:E18),0)) -> 0 | H18: =IF(E18=0,D18,0) -> 0 | I18: =IF(E18=0,C18+D18,0) -> 0 | K18: =IF(B18>Assumptions!$B$6*12+Assumptions!$B$7,"",C18) -> -36291177 | L18: =IF(B18>Assumptions!$B$6*12+Assumptions!$B$7,"",K18/(1+Assumptions!$B$11)^B18) -> -23850382
A19: 46686 | B19: =B18+1 -> 18 | C19: =C18+D19+E19 -> -37281174 | D19: =C18*Assumptions!$B$10^30.5-C18 -> -989996.99 | E19: =IF(CashFlow!B19<Assumptions!$B$7+1,0,IF(AND(B19>=Assumptions!$B$7,SUM($E$2:E18)<>Assumptions!$B$3),Assumptions!$B$3/(Assumptions!$B$6*12),IF(Assumptions!$B$3=SUM($E$3:E19)=0,0,0))) -> 0 | F19: =IF(B19<Assumptions!$B$7+1,0,IF(E18<0,Assumptions!$B$3-SUM($E$3:E19),0)) -> 0 | H19: =IF(E19=0,D19,0) -> -989996.99 | I19: =IF(E19=0,C19+D19,0) -> -38271171 | K19: =IF(B19>Assumptions!$B$6*12+Assumptions!$B$7,"",C19) | L19: =IF(B19>Assumptions!$B$6*12+Assumptions!$B$7,"",K19/(1+Assumptions!$B$11)^B19)
A20: 46717 | B20: =B19+1 -> 19 | C20: =C19+D20+E20 -> -38298177 | D20: =C19*Assumptions!$B$10^30.5-C19 -> -1017003.4 | E20: =IF(CashFlow!B20<Assumptions!$B$7+1,0,IF(AND(B20>=Assumptions!$B$7,SUM($E$2:E19)<>Assumptions!$B$3),Assumptions!$B$3/(Assumptions!$B$6*12),IF(Assumptions!$B$3=SUM($E$3:E20)=0,0,0))) -> 0 | F20: =IF(B20<Assumptions!$B$7+1,0,IF(E19<0,Assumptions!$B$3-SUM($E$3:E20),0)) -> 0 | H20: =IF(E20=0,D20,0) -> -1017003.4 | I20: =IF(E20=0,C20+D20,0) -> -39315181 | K20: =IF(B20>Assumptions!$B$6*12+Assumptions!$B$7,"",C20) | L20: =IF(B20>Assumptions!$B$6*12+Assumptions!$B$7,"",K20/(1+Assumptions!$B$11)^B20)
A21: 46747 | B21: =B20+1 -> 20 | C21: =C20+D21+E21 -> -39342924 | D21: =C20*Assumptions!$B$10^30.5-C20 -> -1044746.5 | E21: =IF(CashFlow!B21<Assumptions!$B$7+1,0,IF(AND(B21>=Assumptions!$B$7,SUM($E$2:E20)<>Assumptions!$B$3),Assumptions!$B$3/(Assumptions!$B$6*12),IF(Assumptions!$B$3=SUM($E$3:E21)=0,0,0))) -> 0 | F21: =IF(B21<Assumptions!$B$7+1,0,IF(E20<0,Assumptions!$B$3-SUM($E$3:E21),0)) -> 0 | H21: =IF(E21=0,D21,0) -> -1044746.5 | I21: =IF(E21=0,C21+D21,0) -> -40387671 | K21: =IF(B21>Assumptions!$B$6*12+Assumptions!$B$7,"",C21) | L21: =IF(B21>Assumptions!$B$6*12+Assumptions!$B$7,"",K21/(1+Assumptions!$B$11)^B21)
A22: 46778 | B22: =B21+1 -> 21 | C22: =C21+D22+E22 -> -40416170 | D22: =C21*Assumptions!$B$10^30.5-C21 -> -1073246.4 | E22: =IF(CashFlow!B22<Assumptions!$B$7+1,0,IF(AND(B22>=Assumptions!$B$7,SUM($E$2:E21)<>Assumptions!$B$3),Assumptions!$B$3/(Assumptions!$B$6*12),IF(Assumptions!$B$3=SUM($E$3:E22)=0,0,0))) -> 0 | F22: =IF(B22<Assumptions!$B$7+1,0,IF(E21<0,Assumptions!$B$3-SUM($E$3:E22),0)) -> 0 | H22: =IF(E22=0,D22,0) -> -1073246.4 | I22: =IF(E22=0,C22+D22,0) -> -41489417 | K22: =IF(B22>Assumptions!$B$6*12+Assumptions!$B$7,"",C22) | L22: =IF(B22>Assumptions!$B$6*12+Assumptions!$B$7,"",K22/(1+Assumptions!$B$11)^B22)
A23: 46809 | B23: =B22+1 -> 22 | C23: =C22+D23+E23 -> -41518694 | D23: =C22*Assumptions!$B$10^30.5-C22 -> -1102523.8 | E23: =IF(CashFlow!B23<Assumptions!$B$7+1,0,IF(AND(B23>=Assumptions!$B$7,SUM($E$2:E22)<>Assumptions!$B$3),Assumptions!$B$3/(Assumptions!$B$6*12),IF(Assumptions!$B$3=SUM($E$3:E23)=0,0,0))) -> 0 | F23: =IF(B23<Assumptions!$B$7+1,0,IF(E22<0,Assumptions!$B$3-SUM($E$3:E23),0)) -> 0 | H23: =IF(E23=0,D23,0) -> -1102523.8 | I23: =IF(E23=0,C23+D23,0) -> -42621218 | K23: =IF(B23>Assumptions!$B$6*12+Assumptions!$B$7,"",C23) | L23: =IF(B23>Assumptions!$B$6*12+Assumptions!$B$7,"",K23/(1+Assumptions!$B$11)^B23)
A24: 46838 | B24: =B23+1 -> 23 | C24: =C23+D24+E24 -> -42651294 | D24: =C23*Assumptions!$B$10^30.5-C23 -> -1132599.9 | E24: =IF(CashFlow!B24<Assumptions!$B$7+1,0,IF(AND(B24>=Assumptions!$B$7,SUM($E$2:E23)<>Assumptions!$B$3),Assumptions!$B$3/(Assumptions!$B$6*12),IF(Assumptions!$B$3=SUM($E$3:E24)=0,0,0))) -> 0 | F24: =IF(B24<Assumptions!$B$7+1,0,IF(E23<0,Assumptions!$B$3-SUM($E$3:E24),0)) -> 0 | H24: =IF(E24=0,D24,0) -> -1132599.9 | I24: =IF(E24=0,C24+D24,0) -> -43783894 | K24: =IF(B24>Assumptions!$B$6*12+Assumptions!$B$7,"",C24) | L24: =IF(B24>Assumptions!$B$6*12+Assumptions!$B$7,"",K24/(1+Assumptions!$B$11)^B24)
A25: 46869 | B25: =B24+1 -> 24 | C25: =C24+D25+E25 -> -43814790 | D25: =C24*Assumptions!$B$10^30.5-C24 -> -1163496.4 | E25: =IF(CashFlow!B25<Assumptions!$B$7+1,0,IF(AND(B25>=Assumptions!$B$7,SUM($E$2:E24)<>Assumptions!$B$3),Assumptions!$B$3/(Assumptions!$B$6*12),IF(Assumptions!$B$3=SUM($E$3:E25)=0,0,0))) -> 0 | F25: =IF(B25<Assumptions!$B$7+1,0,IF(E24<0,Assumptions!$B$3-SUM($E$3:E25),0)) -> 0 | H25: =IF(E25=0,D25,0) -> -1163496.4 | I25: =IF(E25=0,C25+D25,0) -> -44978287 | K25: =IF(B25>Assumptions!$B$6*12+Assumptions!$B$7,"",C25) | L25: =IF(B25>Assumptions!$B$6*12+Assumptions!$B$7,"",K25/(1+Assumptions!$B$11)^B25)
... A72: 48299 | B72: =B71+1 -> 71 | C72: =C71+D72+E72 -> -1.5523208e+08 | D72: =C71*Assumptions!$B$10^30.5-C71 -> -4122168.8 | E72: =IF(CashFlow!B72<Assumptions!$B$7+1,0,IF(AND(B72>=Assumptions!$B$7,SUM($E$2:E71)<>Assumptions!$B$3),Assumptions!$B$3/(Assumptions!$B$6*12),IF(Assumptions!$B$3=SUM($E$3:E72)=0,0,0))) -> 0 | F72: =IF(B72<Assumptions!$B$7+1,0,IF(E71<0,Assumptions!$B$3-SUM($E$3:E72),0)) -> 0 | H72: =IF(E72=0,D72,0) -> -4122168.8 | I72: =IF(E72=0,C72+D72,0) -> -1.5935425e+08 | K72: =IF(B72>Assumptions!$B$6*12+Assumptions!$B$7,"",C72) | L72: =IF(B72>Assumptions!$B$6*12+Assumptions!$B$7,"",K72/(1+Assumptions!$B$11)^B72)
